smack_app/__init__.py
smack_app/app.py
smack_app/cli_validation.py
smack_app/collect_variants.py
smack_app/filter_barcodes.py
smack_app/filter_variants.py
smack_app/genotyping/ConsensusGroup.py
smack_app/genotyping/UMI.py
smack_app/genotyping/__init__.py
smack_app/genotyping/eUMI.py
smack_app/genotyping/h5_schema.py
smack_app/genotyping/run_consensus_variant_calling.py
smack_app/reference/fasta_files/GRCh37.fasta
smack_app/reference/fasta_files/GRCh38.fasta
smack_app/reference/fasta_files/GRCm38.fasta
smack_app/reference/fasta_files/GRCz10.fasta
smack_app/reference/fasta_files/NC_012920.fasta
smack_app/reference/fasta_files/hg19.fasta
smack_app/reference/fasta_files/hg19_chrM.fasta
smack_app/reference/fasta_files/hg38.fasta
smack_app/reference/fasta_files/mm10.fasta
smack_app/reference/fasta_files/mm9.fasta
smack_app/reference/fasta_files/rCRS.fasta
smack_app/reference/genome_reference.py
smack_app/test_app.py
smack_app/test_fixtures/UMI.bam
smack_app/test_fixtures/UMI.bam.bai
smack_app/test_fixtures/custom_genome_MT.fasta
smack_app/test_fixtures/custom_genome_chrM.fasta
smack_app/test_fixtures/full_size_bam.bam
smack_app/test_fixtures/full_size_bam.bam.bai
smack_app/test_fixtures/sample_bam.bam
smack_app/test_fixtures/sample_bam.bam.bai
smack_app/utils/__init__.py
smack_app/utils/bam_splitter.py
smack_app/utils/utils.py
smack_app/variant_filters/filter_sets.py
smack_app/variant_filters/position_bias.py
smack_app/variant_filters/strand_correlation.py
smack_app/variant_filters/vmr.py
smack_app-0.1.15.dist-info/LICENSE
smack_app-0.1.15.dist-info/METADATA
smack_app-0.1.15.dist-info/WHEEL
smack_app-0.1.15.dist-info/entry_points.txt
smack_app-0.1.15.dist-info/RECORD
