Metadata-Version: 2.1
Name: smack-app
Version: 0.1.15
Summary: Single-cell Mitochondrial Analysis CLI Kit
Author: jonlevi
Author-email: jonalevine1@gmail.com
Requires-Python: >=3.11,<4.0
Classifier: Programming Language :: Python :: 3
Classifier: Programming Language :: Python :: 3.11
Classifier: Programming Language :: Python :: 3.12
Classifier: Programming Language :: Python :: 3.13
Requires-Dist: h5py (>=3.12.1,<4.0.0)
Requires-Dist: numpy (>=2.1.3,<3.0.0)
Requires-Dist: pandas (>=2.2.3,<3.0.0)
Requires-Dist: pysam (>=0.22.1,<0.23.0)
Requires-Dist: pytest (>=8.3.3,<9.0.0)
Requires-Dist: scikit-learn (>=1.5.2,<2.0.0)
Requires-Dist: scipy (>=1.14.1,<2.0.0)
Requires-Dist: tables (>=3.10.1,<4.0.0)
Requires-Dist: tqdm (>=4.67.0,<5.0.0)
Requires-Dist: typer (>=0.13.0,<0.14.0)
